{
  "users": [
    {
      "user": {
        "id": 1,
        "name": "Emerson Gabriel",
        "userName": "EmersonGS",
        "wishes": {
          "id": 1,
          "description": "Empinar pipa e jogar bola"
        },
        "bio": "Analista atualmente na STT",
        "img": ""
      },
      "id": 4
    },
    {
      "user": {
        "id": 2,
        "name": "Gustavo Gusmão",
        "userName": "GustavoGus",
        "wishes": {
          "id": 1,
          "description": "Fundar a SSTEC"
        },
        "bio": "Analista atualmente na STT",
        "img": ""
      },
      "id": 6
    },
    {
      "user": {
        "name": "Micaelle Marilia",
        "userName": "Mica",
        "wishes": {
          "id": 1,
          "description": "Dev girls"
        },
        "bio": "Desenvolvedora e blogueira",
        "img": ""
      },
      "id": 7
    }
  ],
  "rooms": [
    {
      "rooms": {
        "name": "Matemática",
        "type": "Geometria",
        "members": [
          {
            "idUser": 4
          },
          {
            "idUser": 5
          }
        ],
        "publications": {
          "idUser": 4,
          "description": "Sábado tem aulão de geometria"
        },
        "comments": {
          "idUser": 5,
          "description": "show, estarei lá"
        }
      },
      "id": 1
    }
  ],
  "connectionList": [
    {
      "connectionList": {
        "id": 5,
        "connection": [
          {
            "id": 4,
            "userName": "Emersongs"
          },
          {
            "id": 6,
            "userName": "GustavoGus"
          }
        ],
        "disconnect": [
          {
            "id": 7,
            "userName": "Mica"
          }
        ]
      },
      "id": 1
    }
  ]
}